{
    "spectra": [
        {
            "activePeriodTime": 265.85899999999998,
            "calibration_matrix_name": "n/a",
            "countRate": 219766.08593349103,
            "cursorChannel": 0,
            "cursorEnergy": 0,
            "cursorPointIndex": 0,
            "cursorSet": false,
            "device_businesslogic_version": -1097312616,
            "dpp_parameter": 3,
            "filterName": "KF",
            "filterPosition": 4,
            "finalTemperature": 31.800000000000001,
            "hasStabilityCheck": false,
            "helium_enable": true,
            "initialTemperature": 31.699999999999999,
            "parameters": {
                "current": [
                    230,
                    "uA"
                ],
                "filter_pos": 4,
                "final_pressure": [
                    1000.6336015633638,
                    "mbar"
                ],
                "final_temp": [
                    31.800000000000001,
                    "celsius"
                ],
                "initial_pressure": [
                    1000.7799855156688,
                    "mbar"
                ],
                "initial_temp": [
                    31.699999999999999,
                    "celsius"
                ],
                "live_time": [
                    159.798,
                    "s"
                ],
                "type": "XrsHWParameters",
                "voltage": [
                    13000,
                    "volt"
                ]
            },
            "rawCounts": 58426643,
            "samplePosition": 2,
            "sample_name": "iis20g01en",
            "specto_version": "2.0.0",
            "spectrumSelected": false,
            "spectrum_bin_value_calibration": {
                "bin_index_bounds": {
                    "lower": 0,
                    "upper": 4095
                },
                "bin_index_vs_bin_value": [
                    0,
                    0.10000067370674029
                ],
                "bin_value_bounds": {
                    "lower": 1000,
                    "upper": 40960
                },
                "bin_value_unit_name": "eV",
                "bin_value_vs_bin_index": [
                    0,
                    9.999932629779849
                ],
                "energyCalibrationGainCorrectionFactor": 1.0000067370674028,
                "is_calibrated": true,
                "number_of_bins": 4096
            },
            "spectrum_size": 4096,
            "spinnerEnabled": false,
            "targetTime": 0,
            "timeString": "2020-11-05 16:05",
            "timestamp": 1604592323,
            "totalAccumulatedTime": 300.30700000000002,
            "tubeCurrent": 0.00023000000000000001,
            "tubeVoltage": 13000,
            "validCounts": 35118181,
            "values": [
                0,
                0,
                0,
                0,
                0,
                0,
                0,
                0,
                0,
                0,
                0,
                0,
                0,
                0,
                0,
                0,
                0,
                0,
                0,
                0,
                0,
                0,
                0,
                0,
                0,
                0,
                1,
                1,
                0,
                0,
                2,
                0,
                11,
                7,
                13,
                22,
                22,
                49,
                48,
                67,
                95,
                119,
                142,
                126,
                152,
                178,
                218,
                226,
                257,
                252,
                281,
                267,
                268,
                289,
                301,
                303,
                277,
                284,
                327,
                299,
                256,
                293,
                285,
                269,
                322,
                306,
                309,
                269,
                286,
                313,
                241,
                257,
                277,
                310,
                285,
                295,
                289,
                307,
                276,
                321,
                273,
                298,
                293,
                275,
                283,
                312,
                307,
                291,
                327,
                286,
                282,
                272,
                276,
                288,
                282,
                267,
                324,
                283,
                266,
                259,
                269,
                282,
                291,
                285,
                312,
                286,
                292,
                316,
                313,
                320,
                288,
                316,
                328,
                299,
                295,
                296,
                331,
                285,
                336,
                316,
                310,
                319,
                306,
                309,
                344,
                334,
                303,
                348,
                324,
                340,
                329,
                304,
                298,
                308,
                328,
                333,
                331,
                289,
                337,
                327,
                404,
                424,
                500,
                678,
                800,
                958,
                1189,
                1378,
                1510,
                1588,
                1517,
                1313,
                1082,
                922,
                759,
                598,
                479,
                409,
                408,
                412,
                368,
                366,
                364,
                348,
                356,
                356,
                376,
                366,
                406,
                416,
                451,
                431,
                526,
                537,
                516,
                574,
                581,
                596,
                600,
                505,
                554,
                527,
                584,
                570,
                596,
                630,
                613,
                733,
                728,
                831,
                911,
                991,
                1086,
                1232,
                1331,
                1512,
                1550,
                1618,
                1686,
                1718,
                1761,
                1755,
                1623,
                1574,
                1468,
                1334,
                1286,
                1139,
                1126,
                1070,
                1188,
                1132,
                1161,
                1228,
                1294,
                1258,
                1308,
                1442,
                1457,
                1527,
                1561,
                1679,
                1814,
                1904,
                2060,
                2151,
                2380,
                2587,
                2800,
                2803,
                2919,
                3091,
                3155,
                3183,
                3260,
                3320,
                3475,
                3408,
                3306,
                3411,
                3585,
                3713,
                3607,
                3757,
                3845,
                3854,
                3830,
                3867,
                3959,
                4003,
                4042,
                3994,
                4010,
                3892,
                4027,
                3954,
                3910,
                3863,
                4029,
                4071,
                4241,
                4321,
                4470,
                4616,
                5010,
                5078,
                5590,
                5874,
                6364,
                6542,
                7237,
                7667,
                8486,
                8913,
                9228,
                9733,
                9813,
                9537,
                9030,
                8567,
                7733,
                7197,
                6466,
                5889,
                5317,
                4935,
                4695,
                4202,
                4295,
                3956,
                4095,
                3926,
                4056,
                4311,
                4254,
                4562,
                4773,
                4711,
                4902,
                4787,
                4714,
                4869,
                4643,
                4709,
                4574,
                4634,
                4636,
                4700,
                4444,
                4669,
                4800,
                4874,
                5057,
                5159,
                5306,
                5437,
                5580,
                5729,
                5780,
                5886,
                5828,
                5804,
                5617,
                5752,
                5551,
                5627,
                5638,
                5854,
                5722,
                5698,
                5991,
                6192,
                6109,
                6109,
                6177,
                6356,
                6243,
                6373,
                6303,
                6519,
                6469,
                6597,
                6627,
                6623,
                6783,
                6882,
                6965,
                7195,
                7243,
                7575,
                7510,
                7627,
                8152,
                8396,
                8681,
                9201,
                9891,
                10919,
                12219,
                13906,
                16365,
                19792,
                24157,
                29942,
                35900,
                42470,
                49277,
                54475,
                58469,
                60620,
                59381,
                56210,
                51189,
                45681,
                38696,
                32445,
                26528,
                21800,
                18185,
                15457,
                13987,
                12961,
                12148,
                11905,
                12039,
                12287,
                11931,
                12209,
                12362,
                12398,
                12719,
                12822,
                13631,
                13758,
                14467,
                15203,
                16172,
                17017,
                17604,
                18584,
                19329,
                19707,
                20308,
                19861,
                19813,
                19227,
                18880,
                17975,
                18228,
                17566,
                17780,
                17646,
                17875,
                18016,
                18420,
                18730,
                18986,
                19622,
                19800,
                19959,
                20388,
                20009,
                20701,
                20788,
                20717,
                21497,
                22591,
                24178,
                26879,
                30478,
                35495,
                42513,
                52089,
                63913,
                80092,
                98954,
                124333,
                153762,
                190159,
                231216,
                281996,
                338292,
                399192,
                469236,
                541819,
                617561,
                689477,
                750350,
                800146,
                827188,
                831417,
                813143,
                765420,
                695951,
                609917,
                519445,
                421848,
                334951,
                255582,
                188563,
                136406,
                96360,
                68555,
                48818,
                36082,
                28575,
                23996,
                21316,
                20185,
                20177,
                20793,
                21424,
                23086,
                25187,
                27471,
                30378,
                34208,
                38247,
                43457,
                49238,
                55796,
                62837,
                70534,
                78801,
                87797,
                96982,
                106067,
                114323,
                122195,
                128675,
                132180,
                134677,
                133819,
                129745,
                121839,
                112505,
                100173,
                87673,
                74415,
                61909,
                50694,
                41018,
                32568,
                26650,
                21940,
                18533,
                16292,
                14777,
                14034,
                13405,
                12859,
                12844,
                12422,
                12750,
                12652,
                12852,
                12754,
                12860,
                13085,
                12999,
                13251,
                13364,
                13475,
                13511,
                13405,
                13604,
                13657,
                13672,
                13954,
                14163,
                14140,
                14137,
                14305,
                14169,
                14532,
                14446,
                14515,
                14570,
                14870,
                14748,
                14862,
                14939,
                15255,
                15196,
                15247,
                15200,
                15298,
                15369,
                15226,
                15305,
                15615,
                15668,
                15804,
                15709,
                15632,
                15872,
                15981,
                16272,
                15864,
                16136,
                16304,
                16107,
                16429,
                16465,
                16367,
                16711,
                16832,
                16546,
                16843,
                17090,
                17065,
                17191,
                17203,
                17348,
                17641,
                17555,
                17412,
                17747,
                17816,
                17921,
                18129,
                18501,
                18247,
                18507,
                18652,
                19042,
                19118,
                19534,
                19402,
                19718,
                19686,
                19602,
                19781,
                19559,
                19526,
                19830,
                19708,
                19586,
                19769,
                19673,
                19685,
                19685,
                20176,
                20146,
                20052,
                20307,
                20003,
                20181,
                20319,
                20484,
                20189,
                20587,
                20515,
                20531,
                20927,
                20888,
                21144,
                21028,
                21308,
                21363,
                21544,
                21682,
                21940,
                21956,
                22276,
                22361,
                22266,
                22549,
                22509,
                22979,
                22831,
                23076,
                23415,
                23512,
                23490,
                23775,
                23794,
                24062,
                24074,
                23866,
                24050,
                24021,
                24142,
                24067,
                24003,
                23918,
                23536,
                23515,
                23876,
                23350,
                23384,
                23275,
                23500,
                23440,
                23493,
                23438,
                23568,
                23331,
                23642,
                23547,
                23845,
                23749,
                23580,
                23999,
                24109,
                23822,
                24084,
                24124,
                23904,
                24041,
                24253,
                24187,
                24338,
                24216,
                24483,
                24483,
                24550,
                24400,
                24705,
                24700,
                24457,
                24716,
                24902,
                24854,
                24890,
                25173,
                24987,
                25147,
                25109,
                25095,
                25570,
                25473,
                25187,
                25101,
                25686,
                25185,
                25363,
                25591,
                25553,
                25781,
                25563,
                25925,
                25743,
                25667,
                25824,
                25417,
                25570,
                25598,
                25713,
                25589,
                25655,
                25710,
                25810,
                25816,
                25658,
                25811,
                25773,
                25918,
                25947,
                25607,
                26282,
                25937,
                25929,
                26265,
                26026,
                26036,
                26012,
                26258,
                26191,
                26501,
                26078,
                26385,
                26650,
                26426,
                26475,
                26705,
                26457,
                26246,
                26270,
                26448,
                26446,
                26678,
                26269,
                26240,
                26803,
                26419,
                26798,
                26631,
                26699,
                26511,
                26398,
                26391,
                26796,
                26737,
                26648,
                26562,
                26614,
                26340,
                26597,
                26496,
                26459,
                26701,
                26717,
                26511,
                26540,
                26589,
                26425,
                26643,
                26848,
                26704,
                26734,
                26871,
                26802,
                26710,
                27037,
                26741,
                26791,
                26855,
                26757,
                26953,
                26845,
                27010,
                26978,
                27035,
                27247,
                27092,
                27096,
                27184,
                27291,
                27120,
                26948,
                27290,
                27168,
                27569,
                27763,
                27063,
                27138,
                27454,
                27321,
                27593,
                27188,
                27540,
                27293,
                27661,
                27607,
                27572,
                27734,
                27958,
                28034,
                27843,
                27875,
                27645,
                28041,
                28151,
                28148,
                28530,
                28470,
                28092,
                28425,
                28163,
                28551,
                28325,
                28426,
                28223,
                27758,
                27962,
                27847,
                27744,
                27616,
                27637,
                27832,
                27799,
                27680,
                27836,
                27388,
                27778,
                27671,
                27406,
                27450,
                27609,
                27769,
                27898,
                27746,
                27374,
                27736,
                27614,
                27492,
                27766,
                27867,
                27689,
                27860,
                27960,
                28117,
                27692,
                27764,
                27989,
                28216,
                27917,
                28126,
                28182,
                28257,
                27848,
                27976,
                28055,
                27968,
                28057,
                28153,
                28038,
                28345,
                28057,
                28304,
                28248,
                28556,
                28690,
                28732,
                28866,
                28855,
                29237,
                29620,
                29534,
                30080,
                30734,
                30755,
                31026,
                31823,
                32342,
                32916,
                33866,
                33934,
                34937,
                35618,
                35688,
                36493,
                36883,
                37353,
                37672,
                37527,
                38139,
                37750,
                37749,
                37786,
                37240,
                36479,
                35718,
                34977,
                34148,
                33529,
                32516,
                31917,
                31467,
                30397,
                30259,
                29588,
                29372,
                28968,
                28615,
                28557,
                28575,
                28585,
                28852,
                28585,
                28696,
                28599,
                28990,
                29042,
                28696,
                29040,
                29543,
                29449,
                29594,
                29599,
                29837,
                30173,
                30346,
                30310,
                30687,
                30455,
                30581,
                30914,
                30850,
                30768,
                30672,
                30301,
                30107,
                30016,
                29866,
                29503,
                29063,
                29261,
                29236,
                28219,
                28398,
                28251,
                28026,
                27995,
                27709,
                27487,
                27372,
                27659,
                27500,
                27302,
                27413,
                27387,
                27316,
                27114,
                27287,
                27439,
                27163,
                27034,
                26811,
                27124,
                27281,
                27249,
                27004,
                27287,
                26979,
                26791,
                26988,
                26851,
                26818,
                26720,
                26827,
                26409,
                26809,
                26881,
                26352,
                26620,
                26446,
                26626,
                26425,
                26295,
                26497,
                26123,
                26377,
                26063,
                26226,
                26212,
                26182,
                26029,
                25944,
                25871,
                25906,
                25633,
                25772,
                25523,
                25811,
                25738,
                25362,
                25578,
                25622,
                25189,
                25737,
                25259,
                25528,
                25458,
                25317,
                25460,
                25040,
                25439,
                25011,
                25101,
                25096,
                24887,
                24981,
                24901,
                24979,
                24467,
                24521,
                24605,
                24857,
                24533,
                24589,
                24542,
                24347,
                24407,
                24317,
                24453,
                24301,
                24233,
                24219,
                24042,
                24084,
                23947,
                23877,
                23958,
                23696,
                23794,
                23758,
                23522,
                23445,
                23521,
                23340,
                23243,
                23318,
                23348,
                23229,
                22979,
                22850,
                23041,
                22946,
                22889,
                22863,
                22926,
                22847,
                22559,
                22595,
                22524,
                22674,
                22317,
                22670,
                22289,
                22099,
                22017,
                22180,
                21754,
                22086,
                21991,
                21996,
                21702,
                21814,
                21789,
                21567,
                21168,
                21505,
                21658,
                21181,
                21354,
                20973,
                21177,
                21016,
                20821,
                20642,
                20555,
                20679,
                20555,
                20436,
                20374,
                20161,
                20185,
                20260,
                20066,
                19975,
                19508,
                19586,
                19490,
                19736,
                19679,
                19520,
                19274,
                19426,
                19279,
                19188,
                19016,
                18972,
                19003,
                18831,
                18711,
                18654,
                18830,
                18418,
                18422,
                18114,
                18140,
                18246,
                18124,
                18015,
                18103,
                17821,
                17509,
                17630,
                17606,
                17447,
                17403,
                17348,
                17192,
                17178,
                16997,
                16925,
                17054,
                16659,
                16539,
                16571,
                16478,
                16468,
                16223,
                16412,
                16057,
                15973,
                15868,
                15813,
                15735,
                15395,
                15405,
                15464,
                15203,
                14993,
                15278,
                14931,
                15105,
                14806,
                14571,
                14342,
                14432,
                14335,
                13920,
                14202,
                14175,
                13853,
                13813,
                13532,
                13696,
                13418,
                13286,
                13249,
                13103,
                13212,
                12745,
                12841,
                12673,
                12525,
                12565,
                12123,
                12113,
                12147,
                12114,
                11997,
                11635,
                11599,
                11576,
                11456,
                11298,
                11195,
                11378,
                10839,
                10862,
                10916,
                10583,
                10541,
                10579,
                10292,
                10299,
                9968,
                10047,
                10034,
                9768,
                9849,
                9678,
                9523,
                9359,
                9171,
                9044,
                8911,
                8816,
                8477,
                8576,
                8320,
                8205,
                8238,
                7967,
                7867,
                7753,
                7627,
                7535,
                7306,
                7171,
                7194,
                6972,
                6929,
                6869,
                6591,
                6510,
                6288,
                6347,
                6050,
                5963,
                5903,
                5747,
                5659,
                5387,
                5361,
                5102,
                5151,
                4966,
                4938,
                4810,
                4541,
                4424,
                4400,
                4298,
                4175,
                4057,
                3868,
                3882,
                3860,
                3580,
                3608,
                3488,
                3398,
                3305,
                3349,
                3187,
                3137,
                3092,
                2922,
                2882,
                2907,
                2793,
                2745,
                2672,
                2634,
                2595,
                2490,
                2481,
                2361,
                2376,
                2300,
                2264,
                2165,
                2271,
                2231,
                2208,
                2139,
                2030,
                2026,
                2060,
                2025,
                1992,
                1934,
                1886,
                1855,
                1848,
                1870,
                1801,
                1733,
                1767,
                1728,
                1787,
                1726,
                1730,
                1618,
                1612,
                1526,
                1588,
                1569,
                1536,
                1552,
                1643,
                1532,
                1529,
                1624,
                1597,
                1552,
                1583,
                1563,
                1510,
                1604,
                1487,
                1531,
                1526,
                1581,
                1509,
                1507,
                1577,
                1560,
                1525,
                1487,
                1563,
                1585,
                1536,
                1641,
                1585,
                1647,
                1652,
                1677,
                1603,
                1670,
                1593,
                1599,
                1659,
                1577,
                1597,
                1638,
                1585,
                1649,
                1624,
                1604,
                1591,
                1603,
                1576,
                1620,
                1609,
                1588,
                1637,
                1654,
                1602,
                1574,
                1592,
                1642,
                1596,
                1613,
                1500,
                1610,
                1543,
                1617,
                1489,
                1526,
                1559,
                1597,
                1603,
                1620,
                1622,
                1660,
                1557,
                1607,
                1590,
                1606,
                1615,
                1529,
                1637,
                1580,
                1523,
                1524,
                1548,
                1580,
                1595,
                1639,
                1558,
                1523,
                1612,
                1629,
                1604,
                1592,
                1600,
                1527,
                1566,
                1529,
                1515,
                1557,
                1569,
                1623,
                1575,
                1658,
                1642,
                1516,
                1488,
                1571,
                1518,
                1577,
                1544,
                1525,
                1600,
                1537,
                1515,
                1584,
                1569,
                1556,
                1527,
                1559,
                1531,
                1576,
                1516,
                1571,
                1602,
                1507,
                1465,
                1545,
                1597,
                1607,
                1592,
                1545,
                1614,
                1560,
                1588,
                1555,
                1472,
                1554,
                1551,
                1573,
                1456,
                1526,
                1458,
                1561,
                1509,
                1596,
                1532,
                1543,
                1488,
                1563,
                1443,
                1515,
                1535,
                1486,
                1463,
                1503,
                1477,
                1537,
                1476,
                1496,
                1540,
                1454,
                1472,
                1450,
                1533,
                1441,
                1502,
                1497,
                1517,
                1460,
                1482,
                1522,
                1374,
                1497,
                1482,
                1410,
                1485,
                1421,
                1450,
                1467,
                1529,
                1530,
                1517,
                1438,
                1434,
                1457,
                1406,
                1456,
                1483,
                1495,
                1473,
                1440,
                1432,
                1390,
                1435,
                1420,
                1459,
                1464,
                1415,
                1455,
                1451,
                1489,
                1324,
                1393,
                1394,
                1419,
                1475,
                1407,
                1414,
                1395,
                1415,
                1359,
                1396,
                1413,
                1387,
                1296,
                1404,
                1384,
                1314,
                1365,
                1356,
                1380,
                1373,
                1320,
                1381,
                1403,
                1407,
                1363,
                1382,
                1377,
                1306,
                1343,
                1302,
                1332,
                1341,
                1328,
                1332,
                1259,
                1286,
                1308,
                1286,
                1252,
                1275,
                1272,
                1288,
                1312,
                1319,
                1340,
                1376,
                1335,
                1287,
                1257,
                1270,
                1292,
                1343,
                1308,
                1266,
                1307,
                1214,
                1283,
                1237,
                1240,
                1229,
                1219,
                1212,
                1255,
                1217,
                1208,
                1190,
                1194,
                1141,
                1201,
                1208,
                1179,
                1162,
                1206,
                1199,
                1201,
                1209,
                1176,
                1182,
                1206,
                1154,
                1196,
                1093,
                1200,
                1171,
                1162,
                1122,
                1141,
                1118,
                1163,
                1157,
                1113,
                1124,
                1124,
                1143,
                1066,
                1043,
                1168,
                1132,
                1149,
                1054,
                1100,
                1116,
                1054,
                1060,
                1013,
                1097,
                1097,
                1056,
                1025,
                990,
                1046,
                1017,
                989,
                1007,
                1015,
                1044,
                1066,
                981,
                1026,
                1038,
                1020,
                1012,
                1018,
                969,
                981,
                975,
                1020,
                1018,
                971,
                947,
                1019,
                960,
                886,
                956,
                927,
                946,
                929,
                933,
                909,
                921,
                942,
                926,
                920,
                901,
                895,
                921,
                890,
                901,
                885,
                873,
                834,
                825,
                820,
                895,
                884,
                825,
                845,
                834,
                856,
                812,
                844,
                788,
                809,
                800,
                802,
                792,
                758,
                751,
                786,
                785,
                779,
                809,
                738,
                787,
                717,
                722,
                701,
                694,
                725,
                702,
                705,
                756,
                683,
                676,
                691,
                671,
                724,
                756,
                677,
                689,
                611,
                696,
                628,
                660,
                642,
                647,
                610,
                633,
                623,
                608,
                629,
                590,
                680,
                612,
                631,
                579,
                625,
                603,
                573,
                591,
                573,
                572,
                603,
                537,
                549,
                559,
                601,
                548,
                546,
                530,
                547,
                585,
                544,
                561,
                555,
                569,
                522,
                562,
                505,
                506,
                524,
                530,
                557,
                558,
                492,
                512,
                496,
                481,
                505,
                506,
                519,
                547,
                485,
                509,
                509,
                504,
                511,
                477,
                530,
                492,
                495,
                498,
                481,
                479,
                500,
                494,
                512,
                473,
                515,
                522,
                467,
                454,
                464,
                518,
                474,
                547,
                483,
                462,
                488,
                490,
                479,
                438,
                504,
                438,
                469,
                506,
                461,
                431,
                493,
                476,
                469,
                491,
                445,
                484,
                437,
                440,
                465,
                457,
                446,
                485,
                506,
                468,
                437,
                435,
                449,
                470,
                431,
                443,
                453,
                438,
                452,
                443,
                432,
                453,
                449,
                455,
                496,
                452,
                490,
                524,
                430,
                426,
                455,
                451,
                449,
                437,
                446,
                470,
                440,
                461,
                472,
                471,
                469,
                431,
                472,
                449,
                442,
                433,
                465,
                431,
                399,
                418,
                438,
                436,
                432,
                442,
                410,
                433,
                440,
                439,
                458,
                439,
                475,
                421,
                465,
                397,
                448,
                428,
                437,
                406,
                436,
                419,
                440,
                426,
                408,
                428,
                396,
                419,
                416,
                407,
                451,
                388,
                433,
                404,
                423,
                406,
                426,
                425,
                384,
                374,
                444,
                382,
                413,
                387,
                413,
                442,
                409,
                418,
                411,
                353,
                403,
                392,
                367,
                385,
                360,
                383,
                405,
                376,
                398,
                378,
                394,
                379,
                420,
                364,
                356,
                388,
                373,
                354,
                359,
                368,
                378,
                346,
                390,
                393,
                376,
                379,
                380,
                368,
                393,
                369,
                364,
                376,
                339,
                369,
                363,
                362,
                393,
                384,
                343,
                368,
                366,
                322,
                352,
                351,
                373,
                343,
                355,
                351,
                357,
                377,
                402,
                336,
                364,
                389,
                371,
                315,
                332,
                367,
                373,
                355,
                329,
                357,
                341,
                350,
                352,
                335,
                316,
                351,
                319,
                347,
                322,
                309,
                362,
                338,
                302,
                329,
                337,
                325,
                358,
                348,
                325,
                334,
                332,
                320,
                310,
                323,
                349,
                328,
                337,
                327,
                329,
                306,
                305,
                331,
                311,
                321,
                306,
                326,
                287,
                308,
                311,
                321,
                296,
                286,
                316,
                295,
                307,
                301,
                318,
                301,
                271,
                313,
                313,
                282,
                300,
                326,
                303,
                301,
                281,
                285,
                318,
                280,
                259,
                285,
                286,
                278,
                280,
                280,
                267,
                302,
                291,
                285,
                290,
                277,
                290,
                259,
                260,
                255,
                312,
                256,
                255,
                255,
                261,
                251,
                269,
                255,
                266,
                264,
                294,
                237,
                257,
                276,
                281,
                243,
                274,
                266,
                249,
                230,
                262,
                267,
                253,
                272,
                237,
                243,
                249,
                260,
                248,
                241,
                246,
                254,
                247,
                232,
                232,
                228,
                259,
                250,
                237,
                235,
                251,
                258,
                236,
                217,
                228,
                212,
                213,
                223,
                219,
                214,
                222,
                212,
                216,
                218,
                215,
                201,
                193,
                194,
                226,
                200,
                200,
                217,
                213,
                181,
                205,
                244,
                207,
                204,
                196,
                224,
                185,
                211,
                211,
                212,
                228,
                191,
                240,
                191,
                204,
                221,
                182,
                181,
                182,
                182,
                212,
                195,
                205,
                179,
                183,
                179,
                195,
                180,
                187,
                220,
                161,
                190,
                191,
                214,
                174,
                178,
                176,
                169,
                176,
                177,
                186,
                152,
                171,
                182,
                176,
                159,
                151,
                183,
                161,
                194,
                164,
                163,
                187,
                158,
                154,
                164,
                163,
                157,
                167,
                157,
                162,
                150,
                159,
                159,
                176,
                169,
                163,
                135,
                144,
                144,
                124,
                161,
                144,
                148,
                145,
                152,
                143,
                131,
                140,
                139,
                144,
                130,
                162,
                126,
                162,
                143,
                129,
                140,
                118,
                136,
                130,
                127,
                140,
                144,
                134,
                146,
                131,
                132,
                154,
                119,
                130,
                112,
                118,
                124,
                107,
                133,
                107,
                122,
                125,
                133,
                109,
                112,
                112,
                113,
                120,
                123,
                120,
                116,
                119,
                109,
                101,
                98,
                95,
                113,
                112,
                100,
                102,
                107,
                97,
                108,
                85,
                101,
                109,
                101,
                96,
                104,
                94,
                85,
                103,
                87,
                107,
                89,
                96,
                89,
                87,
                93,
                110,
                104,
                88,
                92,
                101,
                83,
                100,
                90,
                71,
                107,
                81,
                83,
                78,
                73,
                67,
                79,
                104,
                95,
                82,
                71,
                64,
                79,
                79,
                78,
                88,
                75,
                68,
                62,
                57,
                86,
                69,
                80,
                83,
                72,
                75,
                75,
                77,
                86,
                73,
                82,
                61,
                64,
                74,
                72,
                68,
                60,
                70,
                50,
                67,
                61,
                65,
                81,
                63,
                71,
                73,
                69,
                84,
                68,
                61,
                56,
                72,
                45,
                62,
                62,
                47,
                53,
                54,
                54,
                67,
                52,
                63,
                61,
                67,
                49,
                60,
                60,
                63,
                61,
                46,
                51,
                54,
                54,
                47,
                61,
                45,
                42,
                57,
                55,
                56,
                45,
                62,
                46,
                49,
                44,
                39,
                47,
                52,
                51,
                51,
                40,
                52,
                49,
                44,
                42,
                39,
                46,
                46,
                36,
                42,
                36,
                37,
                45,
                37,
                33,
                36,
                39,
                23,
                37,
                43,
                37,
                39,
                35,
                33,
                31,
                29,
                31,
                41,
                47,
                43,
                36,
                38,
                32,
                34,
                36,
                33,
                28,
                43,
                30,
                29,
                41,
                32,
                33,
                30,
                22,
                32,
                27,
                26,
                37,
                28,
                25,
                31,
                26,
                25,
                27,
                22,
                33,
                29,
                31,
                29,
                40,
                15,
                27,
                21,
                34,
                25,
                16,
                19,
                31,
                23,
                18,
                11,
                30,
                24,
                25,
                23,
                26,
                15,
                17,
                26,
                18,
                16,
                11,
                20,
                23,
                17,
                19,
                14,
                15,
                17,
                19,
                25,
                27,
                19,
                17,
                23,
                18,
                15,
                21,
                28,
                17,
                17,
                18,
                21,
                14,
                25,
                24,
                16,
                15,
                19,
                18,
                14,
                19,
                16,
                13,
                19,
                17,
                21,
                16,
                22,
                15,
                22,
                13,
                14,
                11,
                14,
                8,
                22,
                22,
                19,
                14,
                16,
                17,
                20,
                25,
                15,
                11,
                21,
                15,
                16,
                24,
                14,
                14,
                11,
                10,
                11,
                19,
                18,
                16,
                16,
                15,
                9,
                4,
                12,
                14,
                12,
                13,
                8,
                8,
                9,
                9,
                14,
                6,
                14,
                11,
                11,
                6,
                14,
                10,
                13,
                11,
                14,
                11,
                12,
                5,
                13,
                9,
                14,
                14,
                15,
                15,
                9,
                10,
                20,
                13,
                15,
                16,
                6,
                15,
                9,
                16,
                16,
                7,
                9,
                12,
                12,
                9,
                11,
                10,
                5,
                11,
                10,
                9,
                14,
                9,
                6,
                10,
                6,
                9,
                11,
                6,
                6,
                9,
                16,
                11,
                10,
                10,
                8,
                15,
                14,
                6,
                14,
                12,
                13,
                10,
                4,
                7,
                12,
                13,
                13,
                3,
                14,
                8,
                13,
                6,
                11,
                5,
                9,
                13,
                8,
                6,
                7,
                8,
                12,
                14,
                5,
                9,
                5,
                10,
                8,
                11,
                8,
                8,
                11,
                9,
                15,
                10,
                7,
                7,
                7,
                7,
                12,
                7,
                5,
                13,
                11,
                13,
                3,
                12,
                6,
                10,
                11,
                12,
                10,
                13,
                7,
                11,
                8,
                3,
                11,
                8,
                16,
                7,
                6,
                4,
                6,
                9,
                10,
                5,
                11,
                8,
                4,
                7,
                11,
                6,
                4,
                12,
                10,
                12,
                4,
                5,
                8,
                13,
                8,
                6,
                6,
                6,
                6,
                9,
                9,
                5,
                14,
                3,
                13,
                7,
                10,
                7,
                7,
                5,
                7,
                10,
                5,
                8,
                9,
                5,
                7,
                1,
                9,
                4,
                11,
                10,
                5,
                5,
                7,
                8,
                8,
                7,
                7,
                6,
                6,
                7,
                7,
                8,
                8,
                5,
                5,
                7,
                3,
                4,
                5,
                10,
                7,
                4,
                1,
                6,
                1,
                3,
                5,
                6,
                9,
                3,
                5,
                8,
                6,
                3,
                2,
                8,
                6,
                6,
                5,
                8,
                6,
                4,
                8,
                2,
                5,
                8,
                4,
                6,
                11,
                8,
                7,
                5,
                5,
                6,
                6,
                5,
                12,
                5,
                4,
                2,
                6,
                3,
                5,
                5,
                4,
                8,
                7,
                7,
                5,
                6,
                1,
                4,
                6,
                3,
                2,
                4,
                10,
                10,
                3,
                2,
                3,
                5,
                5,
                11,
                10,
                1,
                7,
                6,
                1,
                7,
                7,
                3,
                3,
                5,
                6,
                9,
                6,
                4,
                3,
                4,
                1,
                1,
                4,
                5,
                6,
                6,
                2,
                8,
                2,
                4,
                8,
                2,
                5,
                3,
                4,
                6,
                4,
                4,
                5,
                1,
                0,
                6,
                6,
                6,
                4,
                5,
                6,
                3,
                2,
                4,
                2,
                9,
                5,
                2,
                4,
                2,
                6,
                5,
                4,
                5,
                3,
                5,
                3,
                1,
                8,
                3,
                0,
                4,
                3,
                1,
                3,
                6,
                5,
                4,
                5,
                5,
                4,
                3,
                7,
                6,
                5,
                3,
                3,
                1,
                0,
                7,
                4,
                5,
                3,
                2,
                2,
                10,
                2,
                3,
                5,
                4,
                4,
                1,
                5,
                2,
                2,
                5,
                1,
                4,
                2,
                4,
                3,
                6,
                3,
                0,
                3,
                6,
                2,
                4,
                2,
                2,
                5,
                3,
                4,
                2,
                8,
                5,
                2,
                3,
                1,
                5,
                1,
                3,
                3,
                3,
                4,
                4,
                3,
                6,
                1,
                3,
                5,
                1,
                4,
                0,
                3,
                3,
                0,
                3,
                2,
                1,
                2,
                3,
                3,
                2,
                3,
                3,
                6,
                3,
                0,
                7,
                4,
                3,
                2,
                6,
                3,
                2,
                2,
                2,
                4,
                2,
                3,
                2,
                3,
                3,
                3,
                0,
                1,
                3,
                3,
                1,
                0,
                3,
                2,
                1,
                3,
                2,
                3,
                5,
                1,
                2,
                4,
                3,
                6,
                5,
                1,
                5,
                2,
                2,
                1,
                2,
                0,
                3,
                8,
                2,
                1,
                6,
                2,
                0,
                1,
                3,
                4,
                1,
                4,
                0,
                1,
                1,
                3,
                2,
                0,
                1,
                0,
                5,
                7,
                3,
                4,
                3,
                0,
                2,
                6,
                1,
                1,
                1,
                3,
                5,
                2,
                1,
                2,
                1,
                2,
                3,
                0,
                2,
                1,
                2,
                0,
                2,
                3,
                2,
                3,
                3,
                2,
                2,
                2,
                1,
                0,
                1,
                6,
                3,
                2,
                2,
                1,
                1,
                1,
                1,
                1,
                4,
                0,
                2,
                0,
                2,
                0,
                2,
                2,
                0,
                6,
                1,
                2,
                4,
                1,
                3,
                2,
                3,
                2,
                1,
                2,
                0,
                2,
                0,
                1,
                0,
                2,
                1,
                1,
                1,
                0,
                2,
                2,
                2,
                2,
                2,
                0,
                2,
                0,
                1,
                0,
                3,
                4,
                2,
                9,
                1,
                1,
                1,
                0,
                0,
                1,
                2,
                3,
                0,
                1,
                0,
                2,
                1,
                1,
                2,
                0,
                1,
                2,
                1,
                1,
                1,
                1,
                0,
                1,
                0,
                3,
                0,
                0,
                3,
                1,
                2,
                0,
                1,
                1,
                0,
                2,
                1,
                2,
                2,
                2,
                1,
                1,
                0,
                2,
                0,
                1,
                1,
                1,
                0,
                1,
                2,
                2,
                2,
                2,
                0,
                3,
                0,
                0,
                5,
                1,
                1,
                1,
                2,
                0,
                1,
                2,
                2,
                0,
                1,
                1,
                2,
                2,
                0,
                3,
                2,
                0,
                0,
                1,
                1,
                1,
                0,
                2,
                3,
                2,
                3,
                0,
                1,
                2,
                1,
                0,
                1,
                1,
                1,
                0,
                1,
                3,
                1,
                0,
                2,
                0,
                1,
                1,
                0,
                1,
                0,
                1,
                0,
                3,
                1,
                1,
                0,
                2,
                0,
                1,
                2,
                1,
                1,
                2,
                1,
                0,
                0,
                1,
                2,
                3,
                3,
                0,
                1,
                1,
                0,
                1,
                3,
                1,
                1,
                2,
                0,
                0,
                3,
                1,
                1,
                0,
                0,
                0,
                1,
                1,
                1,
                0,
                1,
                1,
                6,
                0,
                0,
                1,
                1,
                2,
                0,
                1,
                0,
                0,
                0,
                0,
                1,
                2,
                1,
                0,
                2,
                0,
                2,
                0,
                1,
                0,
                0,
                0,
                0,
                0,
                2,
                1,
                0,
                0,
                0,
                1,
                1,
                0,
                0,
                1,
                1,
                0,
                1,
                0,
                0,
                0,
                1,
                0,
                1,
                1,
                0,
                2,
                1,
                1,
                0,
                0,
                0,
                1,
                1,
                0,
                2,
                0,
                0,
                1,
                0,
                0,
                1,
                0,
                1,
                0,
                0,
                0,
                0,
                0,
                1,
                1,
                0,
                3,
                1,
                0,
                1,
                0,
                0,
                2,
                0,
                0,
                0,
                2,
                0,
                0,
                0,
                0,
                1,
                0,
                0,
                0,
                0,
                0,
                0,
                0,
                0,
                2,
                0,
                0,
                0,
                0,
                1,
                1,
                1,
                0,
                1,
                1,
                2,
                0,
                0,
                0,
                0,
                0,
                0,
                2,
                0,
                0,
                1,
                0,
                1,
                1,
                0,
                0,
                0,
                0,
                0,
                0,
                0,
                0,
                0,
                1,
                0,
                0,
                0,
                0,
                0,
                0,
                0,
                0,
                0,
                0,
                0,
                1,
                1,
                1,
                0,
                0,
                1,
                0,
                0,
                0,
                0,
                0,
                0,
                0,
                0,
                0,
                0,
                0,
                0,
                0,
                0,
                1,
                1,
                0,
                0,
                0,
                0,
                0,
                0,
                0,
                0,
                0,
                0,
                0,
                0,
                0,
                1,
                1,
                0,
                1,
                0,
                0,
                0,
                0,
                0,
                0,
                1,
                1,
                1,
                0,
                0,
                0,
                1,
                0,
                0,
                0,
                2,
                0,
                0,
                0,
                0,
                0,
                0,
                0,
                1,
                0,
                0,
                0,
                0,
                0,
                0,
                0,
                0,
                0,
                0,
                0,
                0,
                0,
                0,
                0,
                0,
                0,
                0,
                2,
                1,
                0,
                0,
                0,
                0,
                0,
                0,
                2,
                1,
                0,
                0,
                0,
                0,
                0,
                0,
                0,
                1,
                1,
                0,
                0,
                0,
                0,
                0,
                0,
                0,
                0,
                0,
                0,
                0,
                0,
                0,
                0,
                0,
                0,
                0,
                0,
                0,
                0,
                0,
                0,
                0,
                0,
                0,
                0,
                0,
                1,
                0,
                0,
                0,
                0,
                0,
                0,
                1,
                0,
                0,
                0,
                0,
                0,
                0,
                0,
                0,
                0,
                0,
                0,
                1,
                0,
                0,
                0,
                0,
                0,
                0,
                0,
                0,
                0,
                0,
                1,
                0,
                0,
                0,
                0,
                0,
                0,
                0,
                0,
                0,
                0,
                0,
                0,
                0,
                0,
                0,
                0,
                0,
                1,
                0,
                0,
                0,
                0,
                0,
                0,
                0,
                0,
                0,
                0,
                0,
                0,
                0,
                0,
                1,
                0,
                0,
                0,
                0,
                0,
                0,
                0,
                0,
                0,
                0,
                0,
                1,
                0,
                1,
                0,
                0,
                0,
                0,
                0,
                0,
                0,
                0,
                0,
                0,
                0,
                0,
                0,
                0,
                0,
                1,
                0,
                0,
                0,
                0,
                0,
                0,
                0,
                0,
                1,
                0,
                0,
                0,
                0,
                0,
                0,
                0,
                0,
                0,
                0,
                0,
                0,
                0,
                0,
                0,
                0,
                0,
                0,
                0,
                0,
                0,
                0,
                0,
                0,
                0,
                0,
                0,
                0,
                0,
                0,
                0,
                0,
                0,
                0,
                0,
                0,
                0,
                0,
                0,
                0,
                0,
                0,
                0,
                0,
                0,
                0,
                0,
                0,
                0,
                0,
                0,
                0,
                0,
                0,
                0,
                0,
                0,
                0,
                0,
                0,
                0,
                0,
                0,
                0,
                0,
                0,
                0,
                0,
                0,
                0,
                0,
                0,
                0,
                0,
                0,
                0,
                1,
                0,
                0,
                1,
                0,
                0,
                0,
                0,
                0,
                0,
                1,
                0,
                0,
                0,
                0,
                0,
                0,
                0,
                0,
                0,
                0,
                0,
                0,
                0,
                0,
                0,
                0,
                0,
                0,
                0,
                0,
                0,
                0,
                0,
                0,
                0,
                0,
                0,
                0,
                0,
                0,
                0,
                0,
                0,
                0,
                0,
                0,
                0,
                0,
                0,
                0,
                0,
                0,
                0,
                0,
                0,
                0,
                0,
                0,
                0,
                0,
                0,
                0,
                0,
                0,
                0,
                0,
                0,
                0,
                1,
                0,
                0,
                0,
                0,
                0,
                0,
                0,
                0,
                0,
                0,
                0,
                0,
                0,
                0,
                0,
                0,
                0,
                0,
                0,
                0,
                0,
                0,
                0,
                0,
                0,
                0,
                0,
                1,
                0,
                0,
                0,
                0,
                0,
                0,
                0,
                0,
                0,
                0,
                0,
                0,
                0,
                0,
                0,
                1,
                0,
                0,
                0,
                0,
                0,
                0,
                0,
                0,
                0,
                0,
                0,
                0,
                0,
                0,
                0,
                0,
                0,
                0,
                0,
                0,
                0,
                0,
                0,
                0,
                0,
                0,
                0,
                0,
                0,
                0,
                0,
                0,
                0,
                0,
                0,
                0,
                0,
                0,
                0,
                0,
                0,
                0,
                0,
                0,
                0,
                0,
                0,
                0,
                0,
                0,
                0,
                0,
                0,
                0,
                0,
                0,
                0,
                0,
                0,
                0,
                0,
                0,
                0,
                0,
                0,
                0,
                0,
                0,
                0,
                0,
                0,
                0,
                0,
                0,
                0,
                0,
                0,
                0,
                0,
                0,
                0,
                0,
                0,
                0,
                0,
                0,
                0,
                0,
                0,
                0,
                1,
                0,
                0,
                0,
                0,
                0,
                0,
                1,
                0,
                0,
                0,
                0,
                0,
                0,
                0,
                0,
                0,
                0,
                0,
                0,
                0,
                0,
                0,
                0,
                0,
                0,
                0,
                0,
                0,
                0,
                0,
                0,
                0,
                0,
                0,
                0,
                0,
                0,
                0,
                0,
                0,
                0,
                0,
                0,
                0,
                0,
                1,
                0,
                0,
                0,
                0,
                0,
                0,
                0,
                0,
                0,
                0,
                0,
                0,
                0,
                0,
                0,
                0,
                0,
                0,
                0,
                0,
                0,
                0,
                0,
                0,
                0,
                0,
                0,
                0,
                0,
                0,
                0,
                0,
                0,
                0,
                0,
                0,
                0,
                0,
                0,
                0,
                0,
                0,
                0,
                0,
                0,
                0,
                0,
                0,
                0,
                0,
                0,
                0,
                0,
                0,
                0,
                0,
                0,
                0,
                0,
                0,
                0,
                0,
                0,
                0,
                0,
                0,
                0,
                0,
                0,
                0,
                0,
                0,
                0,
                0,
                0,
                0,
                0,
                0,
                0,
                0,
                0,
                0,
                0,
                0,
                0,
                0,
                0,
                0,
                0,
                0,
                0,
                0,
                0,
                0,
                0,
                0,
                0,
                0,
                0,
                0,
                0,
                0,
                0,
                0,
                0,
                0,
                0,
                0,
                0,
                0,
                0,
                0,
                0,
                0,
                0,
                0,
                0,
                0,
                0,
                0,
                0,
                0,
                0,
                0,
                0,
                0,
                0,
                0,
                0,
                0,
                0,
                0,
                0,
                0,
                0,
                0,
                0,
                0,
                0,
                0,
                0,
                0,
                0,
                0,
                0,
                0,
                0,
                0,
                0,
                0,
                0,
                0,
                0,
                0,
                0,
                0,
                0,
                0,
                0,
                0,
                0,
                0,
                0,
                0,
                0,
                0,
                0,
                1,
                0,
                0,
                0,
                0,
                0,
                0,
                0,
                0,
                0,
                0,
                0,
                0,
                0,
                0,
                0,
                0,
                0,
                0,
                0,
                0,
                0,
                0,
                0,
                0,
                0,
                0,
                0,
                0,
                0,
                0,
                0,
                0,
                0,
                0,
                0
            ]
        }
    ]
}
